japanese_calendar/__init__.py
japanese_calendar/constants.py
japanese_calendar/solar_terms.py
japanese_calendar/utils.py
japanesecalendar-1.0.2.dist-info/LICENSE
japanesecalendar-1.0.2.dist-info/METADATA
japanesecalendar-1.0.2.dist-info/WHEEL
japanesecalendar-1.0.2.dist-info/top_level.txt
japanesecalendar-1.0.2.dist-info/RECORD
