Metadata-Version: 2.1
Name: japanesecalendar
Version: 1.0.2
Summary: check if some day is holiday in Japan
Home-page: https://github.com/hack-fang/japanese-calendar
Author: Hack Fang
Author-email: likai.fang@gmail.com
License: MIT License
Classifier: License :: OSI Approved :: MIT License
Classifier: Programming Language :: Python :: 3
Classifier: Programming Language :: Python :: 3.8
Classifier: Programming Language :: Python :: 3.9
Classifier: Programming Language :: Python :: 3.10
Classifier: Programming Language :: Python :: 3.11
Classifier: Programming Language :: Python :: 3.12
License-File: LICENSE
